mugal_driver/__init__.py
mugal_driver/low_noise_reference/__init__.py
mugal_driver/low_noise_reference/lnr.py
mugal_driver-0.1.0.dist-info/LICENSE
mugal_driver-0.1.0.dist-info/METADATA
mugal_driver-0.1.0.dist-info/WHEEL
mugal_driver-0.1.0.dist-info/top_level.txt
mugal_driver-0.1.0.dist-info/RECORD
