Metadata-Version: 2.1
Name: mugal-driver
Version: 0.1.0
Summary: Device drivers for MugalTech products
Home-page: https://github.com/mugaltech/mugal_driver
Author: BenFre
Author-email: bingcheng7757@gmail.com
License: UNKNOWN
Project-URL: Bug Reports, https://github.com/mugaltech/mugal_driver/issues
Project-URL: Source, https://github.com/mugaltech/mugal_driver
Keywords: driver,signal generator
Platform: UNKNOWN
Classifier: Development Status :: 3 - Alpha
Classifier: Intended Audience :: Developers
Classifier: Topic :: System :: Hardware :: Hardware Drivers
Classifier: License :: OSI Approved :: MIT License
Classifier: Programming Language :: Python :: 3
Classifier: Programming Language :: Python :: 3.6
Classifier: Programming Language :: Python :: 3.7
Classifier: Programming Language :: Python :: 3.8
Classifier: Programming Language :: Python :: 3.9
Classifier: Programming Language :: Python :: 3.10
Classifier: Programming Language :: Python :: 3 :: Only
Requires-Python: >=3.6, <4
License-File: LICENSE
Requires-Dist: pyserial
Requires-Dist: libscrc
